foodspec/__init__.py
foodspec/artifact.py
foodspec/calibration_transfer.py
foodspec/calibration_transfer_dashboard.py
foodspec/check_env.py
foodspec/cli.py
foodspec/cli_plugin.py
foodspec/cli_predict.py
foodspec/cli_protocol.py
foodspec/cli_registry.py
foodspec/config.py
foodspec/harmonization.py
foodspec/hdf5_schema.yaml
foodspec/heating_trajectory.py
foodspec/library_search.py
foodspec/logging_utils.py
foodspec/logo.py
foodspec/matrix_correction.py
foodspec/metrics.py
foodspec/model_lifecycle.py
foodspec/model_registry.py
foodspec/narrative.py
foodspec/output_bundle.py
foodspec/plugin.py
foodspec/preprocessing_pipeline.py
foodspec/protocol_engine.py
foodspec/registry.py
foodspec/reporting.py
foodspec/rq.py
foodspec/spectral_dataset.py
foodspec/spectral_io.py
foodspec/validation.py
foodspec/apps/__init__.py
foodspec/apps/dairy.py
foodspec/apps/heating.py
foodspec/apps/meat.py
foodspec/apps/microbial.py
foodspec/apps/oils.py
foodspec/apps/protocol_validation.py
foodspec/apps/qc.py
foodspec/chemometrics/__init__.py
foodspec/chemometrics/deep.py
foodspec/chemometrics/mixture.py
foodspec/chemometrics/mixture_nnls.py
foodspec/chemometrics/models.py
foodspec/chemometrics/pca.py
foodspec/chemometrics/validation.py
foodspec/chemometrics/vip.py
foodspec/cli/__init__.py
foodspec/cli/__main__.py
foodspec/cli/library_search.py
foodspec/cli/main.py
foodspec/cli/plugin.py
foodspec/cli/predict.py
foodspec/cli/protocol.py
foodspec/cli/publish.py
foodspec/cli/registry.py
foodspec/cli/commands/__init__.py
foodspec/cli/commands/analysis.py
foodspec/cli/commands/data.py
foodspec/cli/commands/modeling.py
foodspec/cli/commands/preprocess.py
foodspec/cli/commands/utils.py
foodspec/cli/commands/workflow.py
foodspec/core/__init__.py
foodspec/core/api.py
foodspec/core/api_diagnostics.py
foodspec/core/api_io.py
foodspec/core/api_modeling.py
foodspec/core/api_preprocess.py
foodspec/core/api_workflows.py
foodspec/core/dataset.py
foodspec/core/hyperspectral.py
foodspec/core/multimodal.py
foodspec-1.0.0.dist-info/METADATA
foodspec-1.0.0.dist-info/WHEEL
foodspec-1.0.0.dist-info/entry_points.txt
foodspec-1.0.0.dist-info/licenses/LICENSE
foodspec-1.0.0.dist-info/RECORD
