Metadata-Version: 2.4
Name: foodspec
Version: 1.0.0
Summary: Gold-standard Raman and FTIR spectroscopy toolkit for food science.
Project-URL: Homepage, https://github.com/chandrasekarnarayana/foodspec
Project-URL: Documentation, https://chandrasekarnarayana.github.io/foodspec/
Project-URL: Source, https://github.com/chandrasekarnarayana/foodspec
Project-URL: Issues, https://github.com/chandrasekarnarayana/foodspec/issues
Project-URL: Discussions, https://github.com/chandrasekarnarayana/foodspec/discussions
Author: foodspec authors
License: MIT License
License-File: LICENSE
Classifier: Development Status :: 5 - Production/Stable
Classifier: Intended Audience :: Science/Research
Classifier: License :: OSI Approved :: MIT License
Classifier: Operating System :: OS Independent
Classifier: Programming Language :: Python :: 3
Classifier: Programming Language :: Python :: 3 :: Only
Classifier: Programming Language :: Python :: 3.10
Classifier: Programming Language :: Python :: 3.11
Classifier: Programming Language :: Python :: 3.12
Classifier: Programming Language :: Python :: 3.13
Classifier: Topic :: Scientific/Engineering :: Chemistry
Classifier: Topic :: Scientific/Engineering :: Information Analysis
Requires-Python: >=3.10
Requires-Dist: h5py>=3.11.0
Requires-Dist: lightgbm>=4.0.0
Requires-Dist: matplotlib>=3.8
Requires-Dist: numpy>=1.24
Requires-Dist: pandas>=2.0
Requires-Dist: pyyaml>=6.0
Requires-Dist: scikit-learn>=1.3
Requires-Dist: scipy>=1.11
Requires-Dist: statsmodels>=0.14
Requires-Dist: typer>=0.9.0
Requires-Dist: xgboost>=1.7.0
Provides-Extra: dev
Requires-Dist: build>=1.0.0; extra == 'dev'
Requires-Dist: mkdocs-git-revision-date-localized-plugin<2.0,>=1.2.0; extra == 'dev'
Requires-Dist: mkdocs-material<10.0,>=9.5.0; extra == 'dev'
Requires-Dist: mkdocs<2.0,>=1.6.0; extra == 'dev'
Requires-Dist: mkdocstrings-python<2.0,>=1.10.0; extra == 'dev'
Requires-Dist: pytest-cov>=5.0.0; extra == 'dev'
Requires-Dist: pytest-timeout>=2.1.0; extra == 'dev'
Requires-Dist: pytest>=8.2.0; extra == 'dev'
Requires-Dist: ruff>=0.5.0; extra == 'dev'
Requires-Dist: twine>=4.0.0; extra == 'dev'
Provides-Extra: docs
Requires-Dist: mkdocs-git-revision-date-localized-plugin<2.0,>=1.2.0; extra == 'docs'
Requires-Dist: mkdocs-material<10.0,>=9.5.0; extra == 'docs'
Requires-Dist: mkdocs<2.0,>=1.6.0; extra == 'docs'
Requires-Dist: mkdocstrings-python<2.0,>=1.10.0; extra == 'docs'
Provides-Extra: viz
Requires-Dist: matplotlib>=3.8; extra == 'viz'
